BDScriptES/__init__.py
BDScriptES/cliente.py
BDScriptES/stine/__init__.py
BDScriptES/stine/addField.py
BDScriptES/stine/author.py
BDScriptES/stine/authorIcon.py
BDScriptES/stine/authorURL.py
BDScriptES/stine/channelID.py
BDScriptES/stine/color.py
BDScriptES/stine/conditions.py
BDScriptES/stine/deleteMessage.py
BDScriptES/stine/description.py
BDScriptES/stine/footer.py
BDScriptES/stine/footerIcon.py
BDScriptES/stine/guildID.py
BDScriptES/stine/image.py
BDScriptES/stine/loop.py
BDScriptES/stine/message.py
BDScriptES/stine/messageID.py
BDScriptES/stine/roleGrant.py
BDScriptES/stine/texto.py
BDScriptES/stine/thumbnail.py
BDScriptES/stine/title.py
BDScriptES/stine/titleURL.py
BDScriptES/stine/var.py
BDScriptES/utils/__init__.py
BDScriptES/utils/handler_error.py
bdscriptes-0.4.9.dist-info/METADATA
bdscriptes-0.4.9.dist-info/WHEEL
bdscriptes-0.4.9.dist-info/top_level.txt
bdscriptes-0.4.9.dist-info/RECORD
