Metadata-Version: 2.1
Name: bdscriptes
Version: 0.4.9
Summary: Esta es la descripción de mi paquete
Home-page: https://github.com/BDScriptES/BDScriptES
Author: The BDS World Team
Author-email: bdscriptes@gmail.com
Classifier: Programming Language :: Python :: 3
Classifier: License :: OSI Approved :: MIT License
Classifier: Operating System :: OS Independent
Requires-Python: >=3.6
Requires-Dist: discord.py
